kokomark/__init__.py
kokomark/watermark.py
kokomark-0.1.1.dist-info/DESCRIPTION.rst
kokomark-0.1.1.dist-info/METADATA
kokomark-0.1.1.dist-info/RECORD
kokomark-0.1.1.dist-info/WHEEL
kokomark-0.1.1.dist-info/metadata.json
kokomark-0.1.1.dist-info/top_level.txt
