Metadata-Version: 2.0
Name: kokomark
Version: 0.1.1
Summary: Library for watermarking images. Used for 3.4.56.7 @ ece.ntua.gr
Home-page: https://github.com/elikatsis/kokomrk
Author: Nikos Kormpakis
Author-email: el10785@mail.ntua.gr
License: MIT
Platform: UNKNOWN
Requires-Python: >=3.5
Requires-Dist: Pillow (==5.0.0)
